tridimensional/main.py
tridimensional-0.0.0.dist-info/LICENSE
tridimensional-0.0.0.dist-info/METADATA
tridimensional-0.0.0.dist-info/WHEEL
tridimensional-0.0.0.dist-info/top_level.txt
tridimensional-0.0.0.dist-info/RECORD
