Metadata-Version: 2.1
Name: tridimensional
Version: 0.0.0
Summary: A collection of 3D utilities for coordinate representation and manipulation.
Author-email: Paulo Sanchez <dev.szblzpaulo@gmail.com>
Project-URL: Homepage, https://github.com/
Project-URL: Bug Tracker, https://github.com/
Classifier: Intended Audience :: Developers
Classifier: Programming Language :: Python :: 3
Classifier: License :: OSI Approved :: GNU General Public License v3 (GPLv3)
Classifier: Operating System :: OS Independent
Requires-Python: >=3.9
License-File: LICENSE
